setup.py
simpleEnum.py
simpleEnum.egg-info/PKG-INFO
simpleEnum.egg-info/SOURCES.txt
simpleEnum.egg-info/dependency_links.txt
simpleEnum.egg-info/top_level.txt