Metadata-Version: 1.1
Name: simpleEnum
Version: 0.0.4
Summary: simpleEnum - A really really simple Python enum class
Home-page: https://github.com/galtza/simpleEnum
Author: Raul Ramos
Author-email: galtza@wokki.me
License: UNKNOWN
Keywords: enum simple python
Platform: any
Classifier: Development Status :: 4 - Beta
Classifier: License :: OSI Approved :: MIT License
Classifier: Operating System :: OS Independent
Classifier: Programming Language :: Python
Classifier: Programming Language :: Python :: 2
Classifier: Environment :: Console
Classifier: Intended Audience :: Developers
Classifier: Topic :: Software Development :: Libraries :: Python Modules
